{
	"name": "databricks_ingestion_p1_data",
	"properties": {
		"activities": [
			{
				"name": "1 ingest_circuits_file",
				"type": "DatabricksNotebook",
				"dependsOn": [],
				"policy": {
					"timeout": "0.12:00:00",
					"retry": 0,
					"retryIntervalInSeconds": 30,
					"secureOutput": false,
					"secureInput": false
				},
				"userProperties": [],
				"typeProperties": {
					"notebookPath": "/Users/mialuakl@gmail.com/ETL-pipelines-with-Azure-Databricks-and-Delta-Lake/2. ingestion/1. ingest_circuits_file",
					"baseParameters": {
						"p_data_source": {
							"value": "@variables('v_data_source')",
							"type": "Expression"
						},
						"p_file_date": {
							"value": "@formatDateTime(pipeline().parameters.p_window_end_date, 'yyyy-MM-dd')",
							"type": "Expression"
						}
					}
				},
				"linkedServiceName": {
					"referenceName": "AzureDatabricks1",
					"type": "LinkedServiceReference"
				}
			},
			{
				"name": "2 ingest_races_file",
				"type": "DatabricksNotebook",
				"dependsOn": [],
				"policy": {
					"timeout": "0.12:00:00",
					"retry": 0,
					"retryIntervalInSeconds": 30,
					"secureOutput": false,
					"secureInput": false
				},
				"userProperties": [],
				"typeProperties": {
					"notebookPath": "/Users/mialuakl@gmail.com/ETL-pipelines-with-Azure-Databricks-and-Delta-Lake/2. ingestion/2.  ingest_race_file",
					"baseParameters": {
						"p_data_source": {
							"value": "@variables('v_data_source')",
							"type": "Expression"
						},
						"p_file_date": {
							"value": "@formatDateTime(pipeline().parameters.p_window_end_date, 'yyyy-MM-dd')",
							"type": "Expression"
						}
					}
				},
				"linkedServiceName": {
					"referenceName": "AzureDatabricks1",
					"type": "LinkedServiceReference"
				}
			},
			{
				"name": "3 ingest constructors",
				"type": "DatabricksNotebook",
				"dependsOn": [],
				"policy": {
					"timeout": "0.12:00:00",
					"retry": 0,
					"retryIntervalInSeconds": 30,
					"secureOutput": false,
					"secureInput": false
				},
				"userProperties": [],
				"typeProperties": {
					"notebookPath": "/Users/mialuakl@gmail.com/ETL-pipelines-with-Azure-Databricks-and-Delta-Lake/2. ingestion/3. ingest constructors.json file",
					"baseParameters": {
						"p_data_source": {
							"value": "@variables('v_data_source')",
							"type": "Expression"
						},
						"p_file_date": {
							"value": "@formatDateTime(pipeline().parameters.p_window_end_date, 'yyyy-MM-dd')",
							"type": "Expression"
						}
					}
				},
				"linkedServiceName": {
					"referenceName": "AzureDatabricks1",
					"type": "LinkedServiceReference"
				}
			},
			{
				"name": "4 ingest driver",
				"type": "DatabricksNotebook",
				"dependsOn": [],
				"policy": {
					"timeout": "0.12:00:00",
					"retry": 0,
					"retryIntervalInSeconds": 30,
					"secureOutput": false,
					"secureInput": false
				},
				"userProperties": [],
				"typeProperties": {
					"notebookPath": "/Users/mialuakl@gmail.com/ETL-pipelines-with-Azure-Databricks-and-Delta-Lake/2. ingestion/4. ingest drivers.json file",
					"baseParameters": {
						"p_data_source": {
							"value": "@variables('v_data_source')",
							"type": "Expression"
						},
						"p_file_date": {
							"value": "@formatDateTime(pipeline().parameters.p_window_end_date, 'yyyy-MM-dd')",
							"type": "Expression"
						}
					}
				},
				"linkedServiceName": {
					"referenceName": "AzureDatabricks1",
					"type": "LinkedServiceReference"
				}
			},
			{
				"name": "5 ingest result",
				"type": "DatabricksNotebook",
				"dependsOn": [],
				"policy": {
					"timeout": "0.12:00:00",
					"retry": 0,
					"retryIntervalInSeconds": 30,
					"secureOutput": false,
					"secureInput": false
				},
				"userProperties": [],
				"typeProperties": {
					"notebookPath": "/Users/mialuakl@gmail.com/ETL-pipelines-with-Azure-Databricks-and-Delta-Lake/2. ingestion/5. ingest results.json file",
					"baseParameters": {
						"p_data_source": {
							"value": "@variables('v_data_source')",
							"type": "Expression"
						},
						"p_file_date": {
							"value": "@formatDateTime(pipeline().parameters.p_window_end_date, 'yyyy-MM-dd')",
							"type": "Expression"
						}
					}
				},
				"linkedServiceName": {
					"referenceName": "AzureDatabricks1",
					"type": "LinkedServiceReference"
				}
			},
			{
				"name": "6 ingest pit stop",
				"type": "DatabricksNotebook",
				"dependsOn": [],
				"policy": {
					"timeout": "0.12:00:00",
					"retry": 0,
					"retryIntervalInSeconds": 30,
					"secureOutput": false,
					"secureInput": false
				},
				"userProperties": [],
				"typeProperties": {
					"notebookPath": "/Users/mialuakl@gmail.com/ETL-pipelines-with-Azure-Databricks-and-Delta-Lake/2. ingestion/6. ingest pit_stops.json file",
					"baseParameters": {
						"p_data_source": {
							"value": "@variables('v_data_source')",
							"type": "Expression"
						},
						"p_file_date": {
							"value": "@formatDateTime(pipeline().parameters.p_window_end_date, 'yyyy-MM-dd')",
							"type": "Expression"
						}
					}
				},
				"linkedServiceName": {
					"referenceName": "AzureDatabricks1",
					"type": "LinkedServiceReference"
				}
			},
			{
				"name": "7 ingest lap times",
				"type": "DatabricksNotebook",
				"dependsOn": [],
				"policy": {
					"timeout": "0.12:00:00",
					"retry": 0,
					"retryIntervalInSeconds": 30,
					"secureOutput": false,
					"secureInput": false
				},
				"userProperties": [],
				"typeProperties": {
					"notebookPath": "/Users/mialuakl@gmail.com/ETL-pipelines-with-Azure-Databricks-and-Delta-Lake/2. ingestion/7. ingest lap_times folder file",
					"baseParameters": {
						"p_data_source": {
							"value": "@variables('v_data_source')",
							"type": "Expression"
						},
						"p_file_date": {
							"value": "@formatDateTime(pipeline().parameters.p_window_end_date, 'yyyy-MM-dd')",
							"type": "Expression"
						}
					}
				},
				"linkedServiceName": {
					"referenceName": "AzureDatabricks1",
					"type": "LinkedServiceReference"
				}
			},
			{
				"name": "8 ingest qualifying",
				"type": "DatabricksNotebook",
				"dependsOn": [],
				"policy": {
					"timeout": "0.12:00:00",
					"retry": 0,
					"retryIntervalInSeconds": 30,
					"secureOutput": false,
					"secureInput": false
				},
				"userProperties": [],
				"typeProperties": {
					"notebookPath": "/Users/mialuakl@gmail.com/ETL-pipelines-with-Azure-Databricks-and-Delta-Lake/2. ingestion/8. ingest qualifying folder file",
					"baseParameters": {
						"p_data_source": {
							"value": "@variables('v_data_source')",
							"type": "Expression"
						},
						"p_file_date": {
							"value": "@formatDateTime(pipeline().parameters.p_window_end_date, 'yyyy-MM-dd')",
							"type": "Expression"
						}
					}
				},
				"linkedServiceName": {
					"referenceName": "AzureDatabricks1",
					"type": "LinkedServiceReference"
				}
			},
			{
				"name": "Get Folder Details",
				"type": "GetMetadata",
				"dependsOn": [],
				"policy": {
					"timeout": "0.12:00:00",
					"retry": 0,
					"retryIntervalInSeconds": 30,
					"secureOutput": false,
					"secureInput": false
				},
				"userProperties": [],
				"typeProperties": {
					"dataset": {
						"referenceName": "ds_raw_Data",
						"type": "DatasetReference",
						"parameters": {
							"p_window_end_date": {
								"value": "@pipeline().parameters.p_window_end_date",
								"type": "Expression"
							}
						}
					},
					"fieldList": [
						"exists"
					],
					"storeSettings": {
						"type": "AzureBlobFSReadSettings",
						"enablePartitionDiscovery": false
					},
					"formatSettings": {
						"type": "JsonReadSettings"
					}
				}
			},
			{
				"name": "If Folder Exisits",
				"type": "IfCondition",
				"dependsOn": [
					{
						"activity": "Get Folder Details",
						"dependencyConditions": [
							"Completed"
						]
					}
				],
				"userProperties": []
			}
		],
		"parameters": {
			"p_window_end_date": {
				"type": "string",
				"defaultValue": "2021-03-21"
			}
		},
		"variables": {
			"v_data_source": {
				"type": "String",
				"defaultValue": "erg"
			}
		},
		"annotations": [],
		"lastPublishTime": "2024-07-04T01:07:58Z"
	},
	"type": "Microsoft.DataFactory/factories/pipelines"
}